odoo/addons/l10n_es_ticketbai_oss/README.rst
odoo/addons/l10n_es_ticketbai_oss/__init__.py
odoo/addons/l10n_es_ticketbai_oss/__manifest__.py
odoo/addons/l10n_es_ticketbai_oss/i18n/es.po
odoo/addons/l10n_es_ticketbai_oss/i18n/eu_ES.po
odoo/addons/l10n_es_ticketbai_oss/models/__init__.py
odoo/addons/l10n_es_ticketbai_oss/models/account_invoice_tax.py
odoo/addons/l10n_es_ticketbai_oss/models/account_tax.py
odoo/addons/l10n_es_ticketbai_oss/models/ticketbai_invoice_tax.py
odoo/addons/l10n_es_ticketbai_oss/static/description/icon.png
odoo/addons/l10n_es_ticketbai_oss/tests/__init__.py
odoo/addons/l10n_es_ticketbai_oss/tests/test_invoice_oss.py
odoo/addons/l10n_es_ticketbai_oss/views/account_tax_views.xml
odoo12_addon_l10n_es_ticketbai_oss-12.0.1.0.0.dist-info/METADATA
odoo12_addon_l10n_es_ticketbai_oss-12.0.1.0.0.dist-info/WHEEL
odoo12_addon_l10n_es_ticketbai_oss-12.0.1.0.0.dist-info/top_level.txt
odoo12_addon_l10n_es_ticketbai_oss-12.0.1.0.0.dist-info/RECORD
